pytest_logging_end_to_end_test_tool/__init__.py
pytest_logging_end_to_end_test_tool/plugin.py
pytest_logging_end_to_end_test_tool-1.0.7.dist-info/entry_points.txt
pytest_logging_end_to_end_test_tool-1.0.7.dist-info/LICENSE
pytest_logging_end_to_end_test_tool-1.0.7.dist-info/WHEEL
pytest_logging_end_to_end_test_tool-1.0.7.dist-info/METADATA
pytest_logging_end_to_end_test_tool-1.0.7.dist-info/RECORD
