Metadata-Version: 2.1
Name: pytest-logging-end-to-end-test-tool
Version: 1.0.7
Summary: 
License: Apache-2.0
Author: Ryan Faircloth
Author-email: ryan@dss-i.com
Requires-Python: >=3.9,<4.0
Classifier: License :: OSI Approved :: Apache Software License
Classifier: Programming Language :: Python :: 3
Classifier: Programming Language :: Python :: 3.10
Classifier: Programming Language :: Python :: 3.9
Requires-Dist: Faker (>=14.0.0,<15.0.0)
Requires-Dist: Jinja2 (>=3.1.2,<4.0.0)
Requires-Dist: PyYAML (>5.0,<7)
Requires-Dist: pytest (>=7.1.2,<8.0.0)
Requires-Dist: requests (>=2.28.1,<3.0.0)
